eeclass_bot/EEAsyncBot.py
eeclass_bot/EEBulletin.py
eeclass_bot/EEChromeDriver.py
eeclass_bot/EEConfig.py
eeclass_bot/EECourse.py
eeclass_bot/EEHomework.py
eeclass_bot/EEMaterial.py
eeclass_bot/__init__.py
eeclass_bot/models/BlockMaterial.py
eeclass_bot/models/Bulletin.py
eeclass_bot/models/BulletinContent.py
eeclass_bot/models/Homework.py
eeclass_bot/models/Material.py
eeclass_bot/models/MaterialContent.py
eeclass_bot-0.0.41.dist-info/LICENCE.txt
eeclass_bot-0.0.41.dist-info/METADATA
eeclass_bot-0.0.41.dist-info/WHEEL
eeclass_bot-0.0.41.dist-info/top_level.txt
eeclass_bot-0.0.41.dist-info/RECORD
